yatl/__init__.py
yatl/helpers.py
yatl/sanitizer.py
yatl/template.py
yatl-20230507.2.dist-info/LICENSE.txt
yatl-20230507.2.dist-info/METADATA
yatl-20230507.2.dist-info/WHEEL
yatl-20230507.2.dist-info/top_level.txt
yatl-20230507.2.dist-info/RECORD
