Metadata-Version: 2.1
Name: yatl
Version: 20230507.2
Summary: Yet Another Teplate Language (it has been around since 2007)
Author-email: Massimo Di Pierro <massimo.dipierro@gmail.com>
Project-URL: Homepage, https://github.com/web2py/yatl
Project-URL: Bug Tracker, https://github.com/web2py/yatl/issues
Project-URL: Documentation, https://py4web.com/_documentation/static/en/chapter-09.html
Classifier: Programming Language :: Python :: 3
Classifier: License :: OSI Approved :: BSD License
Classifier: Operating System :: OS Independent
Requires-Python: >=3.7
License-File: LICENSE.txt
